{"id":280,"groups":{"GET SMALLER":{"level":0,"members":["CONTRACT","LESSEN","REDUCE","SHRINK"]},"AIRLINE CLASSES":{"level":1,"members":["BUSINESS","COACH","FIRST","PREMIUM"]},"EXAMINE, AS AN APPLICANT":{"level":2,"members":["CHECK","REVIEW","SCREEN","VET"]},"NOTABLE TV EPISODES":{"level":3,"members":["FINALE","PILOT","PREMIERE","SPECIAL"]}},"startingGroups":[["SHRINK","PILOT","BUSINESS","CONTRACT"],["SPECIAL","COACH","PREMIUM","VET"],["REVIEW","PREMIERE","REDUCE","SCREEN"],["CHECK","FINALE","FIRST","LESSEN"]]}