{"id":1077,"groups":{"STARTING WITH THE SAME SOUND, SPELLED DIFFERENTLY":{"level":0,"members":["WAREHOUSE","WEARABLE","WEREWOLF","WHEREFORE"]},"METAPHORS FOR PUBLIC SCRUTINY":{"level":1,"members":["FISHBOWL","HOT SEAT","MICROSCOPE","SPOTLIGHT"]},"MUPPETS":{"level":2,"members":["ANIMAL","BEAKER","FOZZIE","GONZO"]},"THEY FEATURE A BOSS":{"level":3,"members":["COMPANY","E STREET BAND","MAFIA","VIDEO GAME"]}},"images":{},"startingGroups":[["BEAKER","VIDEO GAME","WEREWOLF","MICROSCOPE"],["MAFIA","WAREHOUSE","FISHBOWL","ANIMAL"],["SPOTLIGHT","COMPANY","GONZO","WEARABLE"],["E STREET BAND","HOT SEAT","WHEREFORE","FOZZIE"]]}